src/2by1MUX.v
//============================================================
// Generic 2-to-1 Multiplexer
// Parameterized bit width
//============================================================
module mux2 #(
    parameter WIDTH = 32
)(
    input  wire [WIDTH-1:0] A,   // input 0
    input  wire [WIDTH-1:0] B,   // input 1
    input  wire             sel, // select signal (0 = A, 1 = B)
    output wire [WIDTH-1:0] Y    // output
);

    assign Y = sel ? B : A;

endmodule

src/Memory.v
//============================================================
// MIPS Data Memory (LW / SW)
// - Fully asynchronous: reads & writes update immediately
// - No clock required
// - Word-addressable: memory[address >> 2]
//============================================================

module data_memory #(
    parameter MEM_SIZE = 1024  // number of 32-bit words
)(
    input  wire        MemWrite,     // store enable
    input  wire        MemRead,      // load enable
    input  wire [31:0] address,      // byte address from ALU
    input  wire [31:0] write_data,   // data to store
    output reg  [31:0] read_data     // load result
);

    // 32-bit word memory
    reg [31:0] memory [0:MEM_SIZE-1];
    integer i;

    // Optional: initialize to zero
    initial begin
        for (i = 0; i < MEM_SIZE; i = i + 1)
            memory[i] = 32'b0;
    end

    //============================================================
    // Asynchronous WRITE (dangerous in real hardware, but fine here)
    //============================================================
    always @(*) begin
        if (MemWrite)
            memory[address[31:2]] = write_data; // immediate update
    end

    //============================================================
    // Asynchronous READ
    //============================================================
    always @(*) begin
        if (MemRead)
            read_data = memory[address[31:2]];
        else
            read_data = 32'b0;
    end

endmodule

src/ALU.v
//============================================================
// MIPS 32-bit ALU
// Supports all required operations for your 16 instructions
// Pure combinational logic (no clock)
//============================================================

module alu(
    input  wire [31:0] A,      // First operand (rs)
    input  wire [31:0] B,      // Second operand (rt or immediate)
    input  wire [3:0]  ALUCtrl,// Operation select from ALU Control
    input  wire [4:0]  shamt,  // Shift amount (for SLL, SRL, SRA)
    output reg  [31:0] Result, // ALU output
    output wire        Zero    // High if result == 0
);

    assign Zero = (Result == 32'b0);

    always @(*) begin
        case (ALUCtrl)

            //=====================
            // Arithmetic
            //=====================
            4'b0000: Result = A + B;          // ADD, ADDI, LW, SW
            4'b0001: Result = A - B;          // SUB

            //=====================
            // Logical ops
            //=====================
            4'b0010: Result = A & B;          // AND, ANDI
            4'b0011: Result = A | B;          // OR, ORI
            4'b0100: Result = A ^ B;          // XOR, XORI
            4'b0101: Result = ~(A | B);       // NOR

            //=====================
            // Shifts
            //=====================
            4'b0110: Result = B << shamt;     // SLL
            4'b0111: Result = B >> shamt;     // SRL (logical shift)
            4'b1000: Result = $signed(B) >>> shamt; // SRA (arithmetic shift)

            //=====================
            // Default case
            //=====================
            default: Result = 32'b0;

        endcase
    end

endmodule

src/SignExtender.v
//============================================================
// Sign Extender
// Default: extend 16-bit immediate to 32 bits
//============================================================
module sign_extender #(
    parameter IN_WIDTH  = 16,
    parameter OUT_WIDTH = 32
)(
    input  wire [IN_WIDTH-1:0]  in,
    output wire [OUT_WIDTH-1:0] out
);

    assign out = {{(OUT_WIDTH-IN_WIDTH){in[IN_WIDTH-1]}}, in};

endmodule

src/RegisterFile.v
module register_file #(
    parameter REG_WIDTH = 32,
    parameter REG_ADDR_BITS = 5,
    parameter NUM_REGS = 1 << REG_ADDR_BITS
)(
    input  wire                      clk,        // clock added
    input  wire                      RegWrite,   // write enable
    input  wire [REG_ADDR_BITS-1:0]  read_reg1,  // read address 1
    input  wire [REG_ADDR_BITS-1:0]  read_reg2,  // read address 2
    input  wire [REG_ADDR_BITS-1:0]  write_reg,  // write address
    input  wire [REG_WIDTH-1:0]      write_data, // data to write
    output wire [REG_WIDTH-1:0]      read_data1, // read data 1
    output wire [REG_WIDTH-1:0]      read_data2  // read data 2
);

    // Register array
    reg [REG_WIDTH-1:0] regs [0:NUM_REGS-1];
    integer i;

    // Initialize all registers to 0
    initial begin
        for (i = 0; i < NUM_REGS; i = i + 1)
            regs[i] = 0;
    end

    // Clocked write
    always @(posedge clk) begin
        if (RegWrite && write_reg != 0)
            regs[write_reg] <= write_data;
    end

    // Combinational read
    assign read_data1 = (read_reg1 == 0) ? 0 : regs[read_reg1];
    assign read_data2 = (read_reg2 == 0) ? 0 : regs[read_reg2];

endmodule

src/ControlUnit.v
//============================================================
// Single-Cycle MIPS Control Unit
// Takes full 32-bit instruction and outputs control signals
// including ALUCtrl (direct control of ALU)
//============================================================

module control_unit(
    input  wire [31:0] instruction,

    // Main datapath control signals
    output reg         RegDst,
    output reg         ALUSrc,
    output reg         MemtoReg,
    output reg         RegWrite,
    output reg         MemRead,
    output reg         MemWrite,
    output reg         Jump,

    // Direct ALU control
    output reg [3:0]   ALUCtrl
);

    // Extract opcode and funct fields
    wire [5:0] opcode = instruction[31:26];
    wire [5:0] funct  = instruction[5:0];

    always @(*) begin

        // Default values (safe)
        RegDst   = 0;
        ALUSrc   = 0;
        MemtoReg = 0;
        RegWrite = 0;
        MemRead  = 0;
        MemWrite = 0;
        Jump     = 0;
        ALUCtrl  = 4'b0000;

        case (opcode)

            //====================================================
            // R-TYPE (opcode = 000000)
            //====================================================
            6'b000000: begin
                RegDst   = 1;    // write to rd
                RegWrite = 1;

                case (funct)
                    6'b100000: ALUCtrl = 4'b0000; // ADD
                    6'b100010: ALUCtrl = 4'b0001; // SUB
                    6'b100100: ALUCtrl = 4'b0010; // AND
                    6'b100101: ALUCtrl = 4'b0011; // OR
                    6'b100111: ALUCtrl = 4'b0101; // NOR
                    6'b100110: ALUCtrl = 4'b0100; // XOR
                    6'b000000: ALUCtrl = 4'b0110; // SLL
                    6'b000010: ALUCtrl = 4'b0111; // SRL
                    6'b000011: ALUCtrl = 4'b1000; // SRA
                    default:   ALUCtrl = 4'b0000; // default safe
                endcase
            end

            //====================================================
            // ADDI (001000)
            //====================================================
            6'b001000: begin
                ALUSrc   = 1;
                RegWrite = 1;
                ALUCtrl  = 4'b0000; // ADD
            end

            //====================================================
            // ANDI (001100)
            //====================================================
            6'b001100: begin
                ALUSrc   = 1;
                RegWrite = 1;
                ALUCtrl  = 4'b0010; // AND
            end

            //====================================================
            // ORI (001101)
            //====================================================
            6'b001101: begin
                ALUSrc   = 1;
                RegWrite = 1;
                ALUCtrl  = 4'b0011; // OR
            end

            //====================================================
            // XORI (001110)
            //====================================================
            6'b001110: begin
                ALUSrc   = 1;
                RegWrite = 1;
                ALUCtrl  = 4'b0100; // XOR
            end

            //====================================================
            // LW (100011)
            //====================================================
            6'b100011: begin
                ALUSrc   = 1;
                RegWrite = 1;
                MemRead  = 1;
                MemtoReg = 1;
                ALUCtrl  = 4'b0000; // ADD (address)
            end

            //====================================================
            // SW (101011)
            //====================================================
            6'b101011: begin
                ALUSrc   = 1;
                MemWrite = 1;
                ALUCtrl  = 4'b0000; // ADD (address)
            end

            //====================================================
            // J (000010)
            //====================================================
            6'b000010: begin
                Jump = 1;
            end

            default: begin
                // Defaults already set
            end

        endcase
    end

endmodule

src/InstructionMemory.v
module instruction_memory #(
    parameter ADDR_WIDTH = 10,
    parameter DATA_WIDTH = 32
)(
    input  wire [31:0] address,
    output reg  [31:0] instruction
);

    reg [DATA_WIDTH-1:0] memory [0:(1<<ADDR_WIDTH)-1];
    integer i;

    initial begin
        // Clear memory with NOPs
        for (i = 0; i < (1<<ADDR_WIDTH); i = i + 1)
            memory[i] = 32'b000000_00000_00000_00000_00000_000000;

        // ------------------------------
        // Test program
        // Arithmetic & Logical operations
        // ------------------------------

        // addi $t0, $zero, 5       ; $t0 = 5
        memory[0] = 32'b001000_00000_01000_0000000000000101;

        // addi $t1, $zero, 10      ; $t1 = 10
        memory[1] = 32'b001000_00000_01001_0000000000001010;

        // add $t2, $t0, $t1         ; $t2 = 5 + 10 = 15
        memory[2] = 32'b000000_01000_01001_01010_00000_100000;

        // sub $t3, $t1, $t0         ; $t3 = 10 - 5 = 5
        memory[3] = 32'b000000_01001_01000_01011_00000_100010;

        // and $t4, $t0, $t1         ; $t4 = 5 & 10 = 0
        memory[4] = 32'b000000_01000_01001_01100_00000_100100;

        // or $t5, $t0, $t1          ; $t5 = 5 | 10 = 15
        memory[5] = 32'b000000_01000_01001_01101_00000_100101;

        // xor $t6, $t0, $t1         ; $t6 = 5 ^ 10 = 15
        memory[6] = 32'b000000_01000_01001_01110_00000_100110;

        // sll $t7, $t1, 2           ; $t7 = 10 << 2 = 40
        memory[7] = 32'b000000_00000_01001_01111_00010_000000;

        // srl $s0, $t1, 1           ; $s0 = 10 >> 1 = 5 (logical shift)
        memory[8] = 32'b000000_00000_01001_10000_00001_000010;

        // sra $s1, $t1, 1           ; $s1 = 10 >> 1 = 5 (arithmetic shift)
        memory[9] = 32'b000000_00000_01001_10001_00001_000011;
    end

    always @(*) begin
        instruction = memory[address[31:2]];
    end

endmodule

src/genericAdder.v
module adder #(
    parameter WIDTH = 32
)(
    input  wire [WIDTH-1:0] A,
    input  wire [WIDTH-1:0] B,
    output wire [WIDTH-1:0] SUM
);

    assign SUM = A + B;

endmodule

src/ProgramCounter.v
module program_counter #(
    input  wire        clk,       // Clock signal
    input  wire        reset,     // Active-high reset
    input  wire [31:0] pc_next,   // Next PC value (from adder or branch logic)
    output reg  [31:0] pc_current // Current PC value (sent to instruction memory)
);

    always @(posedge clk or posedge reset) begin
        if (reset)
            pc_current <= 32'b0;        // Start execution at address 0
        else
            pc_current <= pc_next;      // Update PC each clock cycle
    end

endmodule

src/Top.v
// Code your design here
//============================================================
// TOP-LEVEL SINGLE CYCLE MIPS CPU
// Using 4 muxes:
// 1) RegDst
// 2) ALUSrc
// 3) MemToReg
// 4) Jump
//============================================================

module mips_cpu(
    input wire clk,
    input wire reset
);

    //==============================
    // Program Counter
    //==============================
    wire [31:0] pc_current, pc_next, pc_plus4;

    program_counter PC (
        .clk(clk),
        .reset(reset),
        .pc_next(pc_next),
        .pc_current(pc_current)
    );

    // pc + 4 adder
    adder #(32) PC_ADDER (
        .A(pc_current),
        .B(32'd4),
        .SUM(pc_plus4)
    );

    //==============================
    // Instruction Memory
    //==============================
    wire [31:0] instruction;

    instruction_memory IMEM (
        .address(pc_current),
        .instruction(instruction)
    );

    //==============================
    // Control Unit
    //==============================
    wire RegDst, ALUSrc, MemtoReg, RegWrite, MemRead, MemWrite, Jump;
    wire [3:0] ALUCtrl;

    control_unit CTRL (
        .instruction(instruction),
        .RegDst(RegDst),
        .ALUSrc(ALUSrc),
        .MemtoReg(MemtoReg),
        .RegWrite(RegWrite),
        .MemRead(MemRead),
        .MemWrite(MemWrite),
        .Jump(Jump),
        .ALUCtrl(ALUCtrl)
    );

    //==============================
    // Register File Connections
    //==============================
    wire [4:0] rs = instruction[25:21];
    wire [4:0] rt = instruction[20:16];
    wire [4:0] rd = instruction[15:11];
    wire [4:0] write_reg;

    // REGDST MUX (rd or rt)
    mux2 #(5) MUX_RegDst (
        .A(rt),
        .B(rd),
        .sel(RegDst),
        .Y(write_reg)
    );

    // Register file wires
    wire [31:0] reg_data1, reg_data2, write_data;

    register_file REGFILE (
      	.clk(clk),
      	.RegWrite(RegWrite),
        .read_reg1(rs),
        .read_reg2(rt),
        .write_reg(write_reg),
        .write_data(write_data),
        .read_data1(reg_data1),
        .read_data2(reg_data2)
    );

    //==============================
    // Immediate Generation
    //==============================
    wire [31:0] sign_ext_imm;

    sign_extender SIGNEXT (
        .in(instruction[15:0]),
        .out(sign_ext_imm)
    );

    // ALUSRC MUX (reg2 vs immediate)
    wire [31:0] ALU_inputB;

    mux2 #(32) MUX_ALUSrc (
        .A(reg_data2),
        .B(sign_ext_imm),
        .sel(ALUSrc),
        .Y(ALU_inputB)
    );

    //==============================
    // ALU
    //==============================
    wire [31:0] alu_result;
    wire alu_zero;

    alu ALU (
        .A(reg_data1),
        .B(ALU_inputB),
        .ALUCtrl(ALUCtrl),
        .shamt(instruction[10:6]),
        .Result(alu_result),
        .Zero(alu_zero)
    );

    //==============================
    // Data Memory
    //==============================
    wire [31:0] mem_read_data;

    data_memory DMEM (
        .MemWrite(MemWrite),
        .MemRead(MemRead),
        .address(alu_result),
        .write_data(reg_data2),
        .read_data(mem_read_data)
    );

    // MEMTOREG MUX
    mux2 #(32) MUX_MemtoReg (
        .A(alu_result),
        .B(mem_read_data),
        .sel(MemtoReg),
        .Y(write_data)
    );

    //==============================
    // JUMP Logic
    //==============================
    // Jump target = {PC+4[31:28], instruction[25:0] << 2}
    wire [31:0] jump_target = { pc_plus4[31:28], instruction[25:0], 2'b00 };

    // JUMP MUX
    mux2 #(32) MUX_Jump (
        .A(pc_plus4),
        .B(jump_target),
        .sel(Jump),
        .Y(pc_next)
    );

endmodule

src/tb_Top.v
`timescale 1ns/1ps

module tb_mips_cpu;

    reg clk;
    reg reset;

    mips_cpu DUT (
        .clk(clk),
        .reset(reset)
    );

    // Clock
    always #10 clk = ~clk;

    // Timeout mechanism
    initial begin
        #100000 begin
            $display("\nERROR: Simulation timeout! Test did not complete.");
            $finish;
        end
    end

    initial begin
        $dumpfile("cpu.vcd");
        $dumpvars(0, tb_mips_cpu);

        clk = 0;
        reset = 1;
        #20 reset = 0;

        $display("Starting simulation...");
        #600;  // Wait 600ns (30 clock cycles at 20ns period)
        $display("Simulation complete.");

        $display("\n===== CPU REGISTER CHECK =====");

        // Check all registers based on new program
        check_reg(8,  5,   "$t0");
        check_reg(9,  10,  "$t1");
        check_reg(10, 15,  "$t2");
        check_reg(11, 5,   "$t3");
        check_reg(12, 0,   "$t4");
        check_reg(13, 15,  "$t5");
        check_reg(14, 15,  "$t6");
        check_reg(15, 40,  "$t7");
        check_reg(16, 5,   "$s0");
        check_reg(17, 5,   "$s1");

        $display("\n===== FULL REGISTER FILE DUMP =====");
        dump_register_file();

        $display("===== TEST COMPLETE =====");
        $finish;
    end

    //===========================
    // Check a single register
    //===========================
    task check_reg(input integer idx, input integer exp, input [31:0] name);
        begin
            if (DUT.REGFILE.regs[idx] !== exp)
                $display("FAIL: %s = %0d (expected %0d)", name, DUT.REGFILE.regs[idx], exp);
            else
                $display("PASS: %s = %0d", name, exp);
        end
    endtask

    //===========================
    // Check memory location
    //===========================
    task check_mem(input integer addr, input integer exp);
        begin
            if (DUT.DMEM.memory[addr] !== exp)
                $display("FAIL: memory[%0d] = %0d (expected %0d)",
                         addr, DUT.DMEM.memory[addr], exp);
            else
                $display("PASS: memory[%0d] = %0d", addr, exp);
        end
    endtask

    //===========================
    // Dump all 32 registers
    //===========================
    task dump_register_file;
        integer i;
        begin
            for (i = 0; i < 32; i = i + 1)
                $display("REG[%0d] = %0d (0x%08h)", i, DUT.REGFILE.regs[i], DUT.REGFILE.regs[i]);
        end
    endtask

endmodule

cpu.vcd
$date
	Fri Nov 28 15:34:49 2025
$end
$version
	Icarus Verilog
$end
$timescale
	1ps
$end
$scope module tb_mips_cpu $end
$var reg 1 ! clk $end
$var reg 1 " reset $end
$scope module DUT $end
$var wire 1 ! clk $end
$var wire 1 " reset $end
$var wire 5 # write_reg [4:0] $end
$var wire 32 $ write_data [31:0] $end
$var wire 32 % sign_ext_imm [31:0] $end
$var wire 5 & rt [4:0] $end
$var wire 5 ' rs [4:0] $end
$var wire 32 ( reg_data2 [31:0] $end
$var wire 32 ) reg_data1 [31:0] $end
$var wire 5 * rd [4:0] $end
$var wire 32 + pc_plus4 [31:0] $end
$var wire 32 , pc_next [31:0] $end
$var wire 32 - pc_current [31:0] $end
$var wire 32 . mem_read_data [31:0] $end
$var wire 32 / jump_target [31:0] $end
$var wire 32 0 instruction [31:0] $end
$var wire 1 1 alu_zero $end
$var wire 32 2 alu_result [31:0] $end
$var wire 1 3 RegWrite $end
$var wire 1 4 RegDst $end
$var wire 1 5 MemtoReg $end
$var wire 1 6 MemWrite $end
$var wire 1 7 MemRead $end
$var wire 1 8 Jump $end
$var wire 32 9 ALU_inputB [31:0] $end
$var wire 1 : ALUSrc $end
$var wire 4 ; ALUCtrl [3:0] $end
$scope module ALU $end
$var wire 5 < shamt [4:0] $end
$var wire 1 1 Zero $end
$var wire 32 = B [31:0] $end
$var wire 4 > ALUCtrl [3:0] $end
$var wire 32 ? A [31:0] $end
$var reg 32 @ Result [31:0] $end
$upscope $end
$scope module CTRL $end
$var wire 6 A opcode [5:0] $end
$var wire 32 B instruction [31:0] $end
$var wire 6 C funct [5:0] $end
$var reg 4 D ALUCtrl [3:0] $end
$var reg 1 : ALUSrc $end
$var reg 1 8 Jump $end
$var reg 1 7 MemRead $end
$var reg 1 6 MemWrite $end
$var reg 1 5 MemtoReg $end
$var reg 1 4 RegDst $end
$var reg 1 3 RegWrite $end
$upscope $end
$scope module DMEM $end
$var wire 1 7 MemRead $end
$var wire 1 6 MemWrite $end
$var wire 32 E address [31:0] $end
$var wire 32 F write_data [31:0] $end
$var parameter 32 G MEM_SIZE $end
$var reg 32 H read_data [31:0] $end
$var integer 32 I i [31:0] $end
$upscope $end
$scope module IMEM $end
$var wire 32 J address [31:0] $end
$var parameter 32 K ADDR_WIDTH $end
$var parameter 32 L DATA_WIDTH $end
$var reg 32 M instruction [31:0] $end
$var integer 32 N i [31:0] $end
$upscope $end
$scope module MUX_ALUSrc $end
$var wire 1 : sel $end
$var wire 32 O Y [31:0] $end
$var wire 32 P B [31:0] $end
$var wire 32 Q A [31:0] $end
$var parameter 32 R WIDTH $end
$upscope $end
$scope module MUX_Jump $end
$var wire 32 S B [31:0] $end
$var wire 1 8 sel $end
$var wire 32 T Y [31:0] $end
$var wire 32 U A [31:0] $end
$var parameter 32 V WIDTH $end
$upscope $end
$scope module MUX_MemtoReg $end
$var wire 32 W A [31:0] $end
$var wire 32 X B [31:0] $end
$var wire 1 5 sel $end
$var wire 32 Y Y [31:0] $end
$var parameter 32 Z WIDTH $end
$upscope $end
$scope module MUX_RegDst $end
$var wire 5 [ A [4:0] $end
$var wire 5 \ B [4:0] $end
$var wire 1 4 sel $end
$var wire 5 ] Y [4:0] $end
$var parameter 32 ^ WIDTH $end
$upscope $end
$scope module PC $end
$var wire 1 ! clk $end
$var wire 32 _ pc_next [31:0] $end
$var wire 1 " reset $end
$var reg 32 ` pc_current [31:0] $end
$upscope $end
$scope module PC_ADDER $end
$var wire 32 a A [31:0] $end
$var wire 32 b B [31:0] $end
$var wire 32 c SUM [31:0] $end
$var parameter 32 d WIDTH $end
$upscope $end
$scope module REGFILE $end
$var wire 1 3 RegWrite $end
$var wire 1 ! clk $end
$var wire 5 e read_reg1 [4:0] $end
$var wire 5 f read_reg2 [4:0] $end
$var wire 32 g write_data [31:0] $end
$var wire 5 h write_reg [4:0] $end
$var wire 32 i read_data2 [31:0] $end
$var wire 32 j read_data1 [31:0] $end
$var parameter 37 k NUM_REGS $end
$var parameter 32 l REG_ADDR_BITS $end
$var parameter 32 m REG_WIDTH $end
$var integer 32 n i [31:0] $end
$upscope $end
$scope module SIGNEXT $end
$var wire 16 o in [15:0] $end
$var wire 32 p out [31:0] $end
$var parameter 32 q IN_WIDTH $end
$var parameter 32 r OUT_WIDTH $end
$upscope $end
$upscope $end
$scope task check_mem $end
$var integer 32 s addr [31:0] $end
$var integer 32 t exp [31:0] $end
$upscope $end
$scope task check_reg $end
$var reg 32 u name [31:0] $end
$var integer 32 v exp [31:0] $end
$var integer 32 w idx [31:0] $end
$upscope $end
$scope task dump_register_file $end
$var integer 32 x i [31:0] $end
$upscope $end
$upscope $end
$enddefinitions $end
$comment Show the parameter values. $end
$dumpall
b100000 r
b10000 q
b100000 m
b101 l
b100000 k
b100000 d
b101 ^
b100000 Z
b100000 V
b100000 R
b100000 L
b1010 K
b10000000000 G
$end
#0
$dumpvars
bx x
bx w
bx v
bx u
bx t
bx s
b101 p
b101 o
b100000 n
b0 j
b0 i
b1000 h
b101 g
b1000 f
b0 e
b100 c
b100 b
b0 a
b0 `
b100 _
b1000 ]
b0 \
b1000 [
b101 Y
b0 X
b101 W
b100 U
b100 T
b1000000000000000010100 S
b0 Q
b101 P
b101 O
b10000000000 N
b100000000010000000000000000101 M
b0 J
b10000000000 I
b0 H
b0 F
b101 E
b0 D
b101 C
b100000000010000000000000000101 B
b1000 A
b101 @
b0 ?
b0 >
b101 =
b0 <
b0 ;
1:
b101 9
08
07
06
05
04
13
b101 2
01
b100000000010000000000000000101 0
b1000000000000000010100 /
b0 .
b0 -
b100 ,
b100 +
b0 *
b0 )
b0 (
b0 '
b1000 &
b101 %
b101 $
b1000 #
1"
0!
$end
#10000
b101 (
b101 F
b101 Q
b101 i
1!
#20000
0!
0"
#30000
b1010 $
b1010 Y
b1010 g
b1010 2
b1010 @
b1010 E
b1010 W
13
1:
b1010 9
b1010 =
b1010 O
b1001 #
b1001 ]
b1001 h
b0 (
b0 F
b0 Q
b0 i
b1010 C
b1001000000000000101000 /
b1001000000000000101000 S
b1010 %
b1010 P
b1010 p
b1010 o
b1001 &
b1001 [
b1001 f
b1000 ,
b1000 T
b1000 _
b100000000010010000000000001010 0
b100000000010010000000000001010 B
b100000000010010000000000001010 M
b1000 +
b1000 U
b1000 c
b100 -
b100 J
b100 `
b100 a
1!
#40000
0!
#50000
b1111 $
b1111 Y
b1111 g
b1010 #
b1010 ]
b1010 h
b1111 2
b1111 @
b1111 E
b1111 W
14
13
0:
b1010 9
b1010 =
b1010 O
b101 )
b101 ?
b101 j
b100000 C
b0 A
b100001001010100000010000000 /
b100001001010100000010000000 S
b101000000100000 %
b101000000100000 P
b101000000100000 p
b101000000100000 o
b1010 *
b1010 \
b1000 '
b1000 e
b1100 ,
b1100 T
b1100 _
b1000010010101000000100000 0
b1000010010101000000100000 B
b1000010010101000000100000 M
b1010 (
b1010 F
b1010 Q
b1010 i
b1100 +
b1100 U
b1100 c
b1000 -
b1000 J
b1000 `
b1000 a
1!
#60000
0!
#70000
b101 $
b101 Y
b101 g
b101 9
b101 =
b101 O
01
b101 2
b101 @
b101 E
b101 W
b1 ;
b1 >
b1 D
13
14
b1011 #
b1011 ]
b1011 h
b101 (
b101 F
b101 Q
b101 i
b1010 )
b1010 ?
b1010 j
b100010 C
b100101000010110000010001000 /
b100101000010110000010001000 S
b101100000100010 %
b101100000100010 P
b101100000100010 p
b101100000100010 o
b1011 *
b1011 \
b1000 &
b1000 [
b1000 f
b1001 '
b1001 e
b10000 ,
b10000 T
b10000 _
b1001010000101100000100010 0
b1001010000101100000100010 B
b1001010000101100000100010 M
b10000 +
b10000 U
b10000 c
b1100 -
b1100 J
b1100 `
b1100 a
1!
#80000
0!
#90000
b0 $
b0 Y
b0 g
11
b0 2
b0 @
b0 E
b0 W
b1010 9
b1010 =
b1010 O
b10 ;
b10 >
b10 D
13
14
b1100 #
b1100 ]
b1100 h
b1010 (
b1010 F
b1010 Q
b1010 i
b101 )
b101 ?
b101 j
b100100 C
b100001001011000000010010000 /
b100001001011000000010010000 S
b110000000100100 %
b110000000100100 P
b110000000100100 p
b110000000100100 o
b1100 *
b1100 \
b1001 &
b1001 [
b1001 f
b1000 '
b1000 e
b10100 ,
b10100 T
b10100 _
b1000010010110000000100100 0
b1000010010110000000100100 B
b1000010010110000000100100 M
b10100 +
b10100 U
b10100 c
b10000 -
b10000 J
b10000 `
b10000 a
1!
#100000
0!
#110000
b1111 $
b1111 Y
b1111 g
01
b1111 2
b1111 @
b1111 E
b1111 W
b11 ;
b11 >
b11 D
13
14
b1101 #
b1101 ]
b1101 h
b100101 C
b100001001011010000010010100 /
b100001001011010000010010100 S
b110100000100101 %
b110100000100101 P
b110100000100101 p
b110100000100101 o
b1101 *
b1101 \
b11000 ,
b11000 T
b11000 _
b1000010010110100000100101 0
b1000010010110100000100101 B
b1000010010110100000100101 M
b11000 +
b11000 U
b11000 c
b10100 -
b10100 J
b10100 `
b10100 a
1!
#120000
0!
#130000
b100 ;
b100 >
b100 D
13
14
b1110 #
b1110 ]
b1110 h
b100110 C
b100001001011100000010011000 /
b100001001011100000010011000 S
b111000000100110 %
b111000000100110 P
b111000000100110 p
b111000000100110 o
b1110 *
b1110 \
b11100 ,
b11100 T
b11100 _
b1000010010111000000100110 0
b1000010010111000000100110 B
b1000010010111000000100110 M
b11100 +
b11100 U
b11100 c
b11000 -
b11000 J
b11000 `
b11000 a
1!
#140000
0!
#150000
b101000 $
b101000 Y
b101000 g
b110 ;
b110 >
b110 D
13
14
b101000 2
b101000 @
b101000 E
b101000 W
b1111 #
b1111 ]
b1111 h
b0 )
b0 ?
b0 j
b0 C
b1001011110001000000000 /
b1001011110001000000000 S
b10 <
b111100010000000 %
b111100010000000 P
b111100010000000 p
b111100010000000 o
b1111 *
b1111 \
b0 '
b0 e
b100000 ,
b100000 T
b100000 _
b10010111100010000000 0
b10010111100010000000 B
b10010111100010000000 M
b100000 +
b100000 U
b100000 c
b11100 -
b11100 J
b11100 `
b11100 a
1!
#160000
0!
#170000
b101 $
b101 Y
b101 g
b111 ;
b111 >
b111 D
13
14
b101 2
b101 @
b101 E
b101 W
b10000 #
b10000 ]
b10000 h
b10 C
b1001100000000100001000 /
b1001100000000100001000 S
b1 <
b11111111111111111000000001000010 %
b11111111111111111000000001000010 P
b11111111111111111000000001000010 p
b1000000001000010 o
b10000 *
b10000 \
b100100 ,
b100100 T
b100100 _
b10011000000001000010 0
b10011000000001000010 B
b10011000000001000010 M
b100100 +
b100100 U
b100100 c
b100000 -
b100000 J
b100000 `
b100000 a
1!
#180000
0!
#190000
b1000 ;
b1000 >
b1000 D
13
14
b10001 #
b10001 ]
b10001 h
b11 C
b1001100010000100001100 /
b1001100010000100001100 S
b11111111111111111000100001000011 %
b11111111111111111000100001000011 P
b11111111111111111000100001000011 p
b1000100001000011 o
b10001 *
b10001 \
b101000 ,
b101000 T
b101000 _
b10011000100001000011 0
b10011000100001000011 B
b10011000100001000011 M
b101000 +
b101000 U
b101000 c
b100100 -
b100100 J
b100100 `
b100100 a
1!
#200000
0!
#210000
11
b0 $
b0 Y
b0 g
b0 9
b0 =
b0 O
b110 ;
b110 >
b110 D
13
14
b0 2
b0 @
b0 E
b0 W
b0 #
b0 ]
b0 h
b0 (
b0 F
b0 Q
b0 i
b0 C
b0 /
b0 S
b0 <
b0 %
b0 P
b0 p
b0 o
b0 *
b0 \
b0 &
b0 [
b0 f
b101100 ,
b101100 T
b101100 _
b0 0
b0 B
b0 M
b101100 +
b101100 U
b101100 c
b101000 -
b101000 J
b101000 `
b101000 a
1!
#220000
0!
#230000
b110000 ,
b110000 T
b110000 _
b110000 +
b110000 U
b110000 c
b101100 -
b101100 J
b101100 `
b101100 a
1!
#240000
0!
#250000
b110100 ,
b110100 T
b110100 _
b110100 +
b110100 U
b110100 c
b110000 -
b110000 J
b110000 `
b110000 a
1!
#260000
0!
#270000
b111000 ,
b111000 T
b111000 _
b111000 +
b111000 U
b111000 c
b110100 -
b110100 J
b110100 `
b110100 a
1!
#280000
0!
#290000
b111100 ,
b111100 T
b111100 _
b111100 +
b111100 U
b111100 c
b111000 -
b111000 J
b111000 `
b111000 a
1!
#300000
0!
#310000
b1000000 ,
b1000000 T
b1000000 _
b1000000 +
b1000000 U
b1000000 c
b111100 -
b111100 J
b111100 `
b111100 a
1!
#320000
0!
#330000
b1000100 ,
b1000100 T
b1000100 _
b1000100 +
b1000100 U
b1000100 c
b1000000 -
b1000000 J
b1000000 `
b1000000 a
1!
#340000
0!
#350000
b1001000 ,
b1001000 T
b1001000 _
b1001000 +
b1001000 U
b1001000 c
b1000100 -
b1000100 J
b1000100 `
b1000100 a
1!
#360000
0!
#370000
b1001100 ,
b1001100 T
b1001100 _
b1001100 +
b1001100 U
b1001100 c
b1001000 -
b1001000 J
b1001000 `
b1001000 a
1!
#380000
0!
#390000
b1010000 ,
b1010000 T
b1010000 _
b1010000 +
b1010000 U
b1010000 c
b1001100 -
b1001100 J
b1001100 `
b1001100 a
1!
#400000
0!
#410000
b1010100 ,
b1010100 T
b1010100 _
b1010100 +
b1010100 U
b1010100 c
b1010000 -
b1010000 J
b1010000 `
b1010000 a
1!
#420000
0!
#430000
b1011000 ,
b1011000 T
b1011000 _
b1011000 +
b1011000 U
b1011000 c
b1010100 -
b1010100 J
b1010100 `
b1010100 a
1!
#440000
0!
#450000
b1011100 ,
b1011100 T
b1011100 _
b1011100 +
b1011100 U
b1011100 c
b1011000 -
b1011000 J
b1011000 `
b1011000 a
1!
#460000
0!
#470000
b1100000 ,
b1100000 T
b1100000 _
b1100000 +
b1100000 U
b1100000 c
b1011100 -
b1011100 J
b1011100 `
b1011100 a
1!
#480000
0!
#490000
b1100100 ,
b1100100 T
b1100100 _
b1100100 +
b1100100 U
b1100100 c
b1100000 -
b1100000 J
b1100000 `
b1100000 a
1!
#500000
0!
#510000
b1101000 ,
b1101000 T
b1101000 _
b1101000 +
b1101000 U
b1101000 c
b1100100 -
b1100100 J
b1100100 `
b1100100 a
1!
#520000
0!
#530000
b1101100 ,
b1101100 T
b1101100 _
b1101100 +
b1101100 U
b1101100 c
b1101000 -
b1101000 J
b1101000 `
b1101000 a
1!
#540000
0!
#550000
b1110000 ,
b1110000 T
b1110000 _
b1110000 +
b1110000 U
b1110000 c
b1101100 -
b1101100 J
b1101100 `
b1101100 a
1!
#560000
0!
#570000
b1110100 ,
b1110100 T
b1110100 _
b1110100 +
b1110100 U
b1110100 c
b1110000 -
b1110000 J
b1110000 `
b1110000 a
1!
#580000
0!
#590000
b1111000 ,
b1111000 T
b1111000 _
b1111000 +
b1111000 U
b1111000 c
b1110100 -
b1110100 J
b1110100 `
b1110100 a
1!
#600000
0!
#610000
b1111100 ,
b1111100 T
b1111100 _
b1111100 +
b1111100 U
b1111100 c
b1111000 -
b1111000 J
b1111000 `
b1111000 a
b100000 x
b1001000111001100110001 u
b101 v
b10001 w
1!
